ox_bqpipeline/__init__.py
ox_bqpipeline/bqpipeline.py
ox_bqpipeline-0.0.4.dist-info/LICENSE
ox_bqpipeline-0.0.4.dist-info/METADATA
ox_bqpipeline-0.0.4.dist-info/WHEEL
ox_bqpipeline-0.0.4.dist-info/top_level.txt
ox_bqpipeline-0.0.4.dist-info/RECORD
