Metadata-Version: 2.1
Name: ox-bqpipeline
Version: 0.0.4
Summary: Utility class for building data pipelines in BigQuery
Home-page: https://github.com/openx/ox-bqpipeline
Author: Jacob Ferriero
Author-email: jferriero@google.com
License: Apache 2.0
Download-URL: https://github.com/openx/ox-bqpipeline/archive/v0.0.4.zip
Platform: Posix; MacOS X; Windows
Classifier: Development Status :: 3 - Alpha
Classifier: Intended Audience :: Developers
Classifier: License :: OSI Approved :: Apache Software License
Classifier: Programming Language :: Python
Classifier: Programming Language :: Python :: 3
Classifier: Programming Language :: Python :: 3.4
Classifier: Programming Language :: Python :: 3.5
Classifier: Programming Language :: Python :: 3.6
Classifier: Programming Language :: Python :: 3.7
Classifier: Operating System :: OS Independent
Classifier: Topic :: Internet
Requires-Python: >=3.4
Requires-Dist: google-cloud (>=0.34.0)
Requires-Dist: google-api-python-client (>=1.7.8)
Requires-Dist: google-cloud-bigquery (>=1.9.0)
Requires-Dist: Jinja2 (>=2.10)
Requires-Dist: j2cli (>=0.3.8)
Requires-Dist: sqlparse (>=0.3.0)
Requires-Dist: pylint (>=1.9.4)
